pycerthole/__init__.py
pycerthole/api.py
pycerthole/domains.py
pycerthole-1.0.dist-info/LICENSE
pycerthole-1.0.dist-info/METADATA
pycerthole-1.0.dist-info/WHEEL
pycerthole-1.0.dist-info/top_level.txt
pycerthole-1.0.dist-info/RECORD
