Metadata-Version: 2.1
Name: pycerthole
Version: 1.0
Summary: Unofficial python 3 library to manage data from https://hole.cert.pl/
Home-page: https://github.com/TheArqsz/pycerthole
Author: Arqsz
Author-email: arqsz@protonmail.com
License: MIT
Keywords: security
Platform: UNKNOWN
Classifier: Programming Language :: Python :: 3
Classifier: License :: OSI Approved :: MIT License
Classifier: Operating System :: OS Independent
Requires-Python: >=3.0
Requires-Dist: requests (==2.23.0)
Requires-Dist: bs4 (==0.0.1)
